{
  "current": {
    "body_bg_color": "#ffffff",
    "body_text_color": "#111111",
    "border_color": "#111111",
    "color_button_text_primary": "#ffffff",
    "color_outline_button": "#ffffff",
    "color_button_secondary": "#9d1339",
    "color_button_text_secondary": "#ffffff",
    "announcement_bg_color": "#111111",
    "announcement_text_color": "#ffffff",
    "header_background_color": "#ffffff",
    "header_text_color": "#111111",
    "footer_text": "#ffffff",
    "heading_font_family": "lato_n6",
    "body_font_family": "futura_n4",
    "cart_type": "drawer",
    "cart_icon": "bag",
    "is_free_shipping_bar": true,
    "free_shipping_threshold": "2000",
    "additional_checkout_buttons": true,
    "show_terms": true,
    "show_note": true,
    "overlay_style": false,
    "show_first_product": false,
    "collection_image_size": "portrait",
    "show_currency": true,
    "show_language": true,
    "show_flags": true,
    "text_direction": "ltr",
    "show_breadcrumbs": true,
    "show_back_to_top": true,
    "back_button_position": "bottom_center",
    "favicon": "shopify:\/\/shop_images\/Vector.svg",
    "image_size": "square",
    "show_quick_view": true,
    "show_color_swatches": true,
    "show_vendor": true,
    "show_second_image": true,
    "sale_badge_color": "#9d1339",
    "soldout_badge_color": "#a6a9ab",
    "social_facebook_url": "facebook.com",
    "social_twitter_url": "twitter.com",
    "social_instagram_url": "instagram.com",
    "social_pinterest_url": "pinterest.com",
    "social_snapchat_url": "",
    "social_tumblr_url": "",
    "social_tiktok_url": "",
    "social_linkedin_url": "",
    "social_youtube_url": "",
    "social_vimeo_url": "",
    "enable_search": true,
    "enable_predictive_search": true,
    "show_add_to_cart": false,
    "show_socials": false,
    "collection_layout": "slider",
    "color_button": "#111111",
    "color_button_text": "#ffffff",
    "sections": {
      "gift-card": {
        "type": "gift-card",
        "settings": {
          "logo": "shopify:\/\/shop_images\/Group_172.png",
          "desktop_logo_width": 110,
          "mobile_logo_width": 110
        }
      }
    },
    "content_for_index": [

    ],
    "blocks": {
      "14060646107696862457": {
        "type": "shopify:\/\/apps\/judge-me-reviews\/blocks\/judgeme_core\/61ccd3b1-a9f2-4160-9fe9-4fec8413e5d8",
        "disabled": false,
        "settings": {
        }
      }
    }
  }
}
