{
  "layout": "password",
  "sections": {
    "main": {
      "type": "main-password",
      "blocks": {
        "2b7286e6-b733-4329-aa10-129da342ea3a": {
          "type": "title",
          "settings": {
            "title": "Opening Soon"
          }
        },
        "47972906-dd99-4f4c-a673-ab1c907e2502": {
          "type": "text",
          "settings": {
            "text": "<p>Be the first to know when we launch.<\/p>"
          }
        },
        "74a55907-38cc-40a3-9537-a059b5472145": {
          "type": "form",
          "settings": {
          }
        },
        "20250be1-81eb-4596-8d2a-3ac9766ef1c9": {
          "type": "socials",
          "settings": {
          }
        }
      },
      "block_order": [
        "2b7286e6-b733-4329-aa10-129da342ea3a",
        "47972906-dd99-4f4c-a673-ab1c907e2502",
        "74a55907-38cc-40a3-9537-a059b5472145",
        "20250be1-81eb-4596-8d2a-3ac9766ef1c9"
      ],
      "settings": {
        "background_image": "shopify:\/\/shop_images\/woman-wearing-native-african-clothing-arid-environment_1.jpg",
        "content_position": "center",
        "text_alignment": "center"
      }
    }
  },
  "order": [
    "main"
  ]
}
